create_artisan_profile/__init__.py
create_artisan_alarms_phidget-0.2.dist-info/METADATA
create_artisan_alarms_phidget-0.2.dist-info/WHEEL
create_artisan_alarms_phidget-0.2.dist-info/entry_points.txt
create_artisan_alarms_phidget-0.2.dist-info/top_level.txt
create_artisan_alarms_phidget-0.2.dist-info/RECORD
